trufl/__init__.py
trufl/_modidx.py
trufl/callbacks.py
trufl/collector.py
trufl/mcdm.py
trufl/optimizer.py
trufl/reader.py
trufl/sampler.py
trufl/utils.py
trufl-0.1.0.dist-info/LICENSE
trufl-0.1.0.dist-info/METADATA
trufl-0.1.0.dist-info/WHEEL
trufl-0.1.0.dist-info/entry_points.txt
trufl-0.1.0.dist-info/top_level.txt
trufl-0.1.0.dist-info/RECORD
