Metadata-Version: 2.1
Name: trufl
Version: 0.1.0
Summary: Optimize adaptive sampling
Home-page: https://github.com/franckalbinet/trufl
Author: Floris Abrams, Franck Albinet
Author-email: franckalbinet@gmail.com
License: Apache Software License 2.0
Keywords: nbdev jupyter notebook python
Classifier: Development Status :: 4 - Beta
Classifier: Intended Audience :: Developers
Classifier: Natural Language :: English
Classifier: Programming Language :: Python :: 3.7
Classifier: Programming Language :: Python :: 3.8
Classifier: Programming Language :: Python :: 3.9
Classifier: Programming Language :: Python :: 3.10
Classifier: License :: OSI Approved :: Apache Software License
Requires-Python: >=3.7
License-File: LICENSE
Requires-Dist: fastcore
Requires-Dist: geopandas
Requires-Dist: rasterio
Requires-Dist: pysal ==24.1
Provides-Extra: dev
